[{"citation-number":["1"],"author":[{"family":"Blaauw","given":"Merlijn"},{"family":"Bonada","given":"Jordi"}],"date":["2017","2017"],"title":["A neural parametric singing synthesizer modeling timbre and expression from natural songs"],"volume":["7, 12"],"pages":["1313"],"type":"article-journal","container-title":["Applied Sciences"]},{"citation-number":["2"],"author":[{"family":"Boersma","given":"Paul"},{"others":true}],"date":["2002","2002"],"title":["Praat, a system for doing phonetics by computer"],"volume":["5"],"type":"article-journal","container-title":["Glot international"]},{"citation-number":["3"],"author":[{"family":"Callan","given":"Jamie"},{"family":"Hoy","given":"Mark"},{"family":"Yoo","given":"Changkuk"},{"family":"Zhao","given":"Le"}],"date":["2009"],"title":["Clueweb09 data set"],"type":null},{"citation-number":["4"],"author":[{"family":"Cao","given":"Zhe"},{"family":"Qin","given":"Tao"},{"family":"Liu","given":"Tie-Yan"},{"family":"Tsai","given":"Ming-Feng"},{"family":"Li","given":"Hang"}],"date":["2007"],"title":["Learning to rank: from pairwise approach to listwise approach"],"container-title":["Proceedings ofthe 24th international conference on Machine learning"],"pages":["129–136"],"type":"paper-conference"},{"citation-number":["5"],"author":[{"family":"Chandna","given":"Pritish"},{"family":"Blaauw","given":"Merlijn"},{"family":"Bonada","given":"Jordi"},{"family":"Gomez","given":"Emilia"}],"date":["2019","2019"],"title":["WGANS- ing: A Multi-Voice Singing Voice Synthesizer Based on the Wasserstein-GAN"],"note":["arXiv preprint arXiv:1903.10729"],"arxiv":["1903.10729"],"type":null},{"citation-number":["6"],"author":[{"family":"Chien","given":"Yu-Ren"},{"family":"Wang","given":"Hsin-Min"},{"family":"Jeng","given":"Shyh-Kang"},{"family":"Chien","given":"Yu-Ren"},{"family":"Wang","given":"Hsin-Min"},{"family":"Jeng","given":"Shyh-Kang"}],"date":["2016","2016"],"title":["Alignment of lyrics with accompanied singing audio based on acoustic-phonetic vowel likelihood modeling"],"volume":["24"],"pages":["11","1998–2008"],"type":"article-journal","container-title":["TASLP"]},{"citation-number":["7"],"author":[{"family":"Dhariwal","given":"Prafulla"},{"family":"Jun","given":"Heewoo"},{"family":"Payne","given":"Christine"},{"family":"Kim","given":"Jong Wook"},{"family":"Radford","given":"Alec"},{"family":"Sutskever","given":"Ilya"}],"date":["2020","2020"],"note":["Jukebox: A generative model for music. arXiv preprint arXiv:2005.00341"],"arxiv":["2005.00341"],"type":null},{"citation-number":["8"],"author":[{"family":"Wang","given":"Zhiyong Zhang Dong"},{"family":"Zhang","given":"Xuewei"}],"date":["2015"],"title":["THCHS-30 : A Free Chinese Speech Corpus"],"url":["http://arxiv.org/abs/1512.01882"],"type":null},{"citation-number":["9"],"author":[{"family":"Dzhambazov","given":"Georgi"},{"others":true}],"date":["2017"],"title":["Knowledge-based probabilistic modeling for tracking lyrics in music audio signals"],"genre":["Ph.D. Dissertation."],"publisher":["Universitat Pompeu Fabra"],"type":"thesis"},{"citation-number":["10"],"author":[{"family":"Fujihara","given":"Hiromasa"},{"family":"Goto","given":"Masataka"},{"family":"Ogata","given":"Jun"},{"family":"Okuno","given":"Hiroshi G."}],"date":["2011","2011"],"title":["Lyric- Synchronizer: Automatic synchronization system between musical audio signals and lyrics"],"volume":["5, 6"],"pages":["1252–1261"],"type":"article-journal","container-title":["IJSTSP"]},{"citation-number":["11"],"author":[{"family":"Griffin","given":"Daniel"},{"family":"Lim","given":"Jae"}],"date":["1984","1984"],"title":["Signal estimation from modified short-time Fourier transform"],"volume":["32, 2"],"pages":["236–243"],"type":"article-journal","container-title":["ICASSP"]},{"citation-number":["12"],"author":[{"family":"Gupta","given":"Chitralekha"},{"family":"Tong","given":"Rong"},{"family":"Li","given":"Haizhou"},{"family":"Wang","given":"Ye"}],"date":["2018"],"title":["Semi-supervised Lyrics and Solo-singing Alignment"],"container-title":["ISMIR"],"pages":["600–607"],"type":"chapter"},{"citation-number":["13"],"author":[{"family":"Gupta","given":"Chitralekha"},{"family":"Yılmaz","given":"Emre"},{"family":"Li","given":"Haizhou"}],"date":["2019","2019"],"title":["Acoustic Modeling for Automatic Lyrics-to-Audio Alignment"],"note":["arXiv preprint arXiv:1906.10369"],"arxiv":["1906.10369"],"type":null},{"citation-number":["14"],"author":[{"family":"Hennequin","given":"Romain"},{"family":"Khlif","given":"Anis"},{"family":"Voituret","given":"Felix"},{"family":"Moussalam","given":"Manuel"}],"date":["2019"],"title":["Spleeter: A fast and state-of-the art music source separation tool with pre-trained models"],"container-title":["Proc. International Society for Music Information Retrieval Conference"],"type":"paper-conference"},{"citation-number":["15"],"author":[{"family":"Hono","given":"Yukiya"},{"family":"Hashimoto","given":"Kei"},{"family":"Oura","given":"Keiichiro"},{"family":"Nankaku","given":"Yoshihiko"},{"family":"Tokuda","given":"Keiichi"}],"date":["2019"],"title":["Singing Voice Synthesis Based on Generative Adversarial Networks"],"container-title":["ICASSP 2019. IEEE"],"pages":["6955–6959"],"type":"chapter"},{"citation-number":["16"],"author":[{"family":"Hunt","given":"Andrew J."},{"family":"Black","given":"Alan W."}],"date":["1996"],"title":["Unit selection in a concatenative speech synthesis system using a large speech database"],"container-title":["ICASSP 1996"],"volume":["1"],"publisher":["IEEE"],"pages":["373–376"],"type":"chapter"},{"citation-number":["17"],"author":[{"family":"Jaeger","given":"Herbert"}],"date":["2002"],"title":["Tutorial on training recurrent neural networks, covering BPPT, RTRL"],"volume":["5"],"publisher":["GMD-Forschungszentrum Informationstechnik Bonn"],"type":"article-journal","container-title":["EKFandthe\" echo state network\" approach"]},{"citation-number":["18"],"author":[{"family":"Kalchbrenner","given":"Nal"},{"family":"Elsen","given":"Erich"},{"family":"Simonyan","given":"Karen"},{"family":"Noury","given":"Seb"},{"family":"Casagrande","given":"Norman"},{"family":"Lockhart","given":"Edward"},{"family":"Stimberg","given":"Florian"},{"family":"Oord","given":"Aaron","particle":"van den"},{"family":"Dieleman","given":"Sander"},{"family":"Kavukcuoglu","given":"Koray"}],"date":["2018","2018"],"note":["Efficient neural audio synthesis. arXiv preprint arXiv:1802.08435"],"arxiv":["1802.08435"],"type":"thesis"},{"citation-number":["19"],"author":[{"family":"Kim","given":"Juntae"},{"family":"Choi","given":"Heejin"},{"family":"Park","given":"Jinuk"},{"family":"Kim","given":"Sangjin"},{"family":"Kim","given":"Jongjin"},{"family":"Hahn","given":"Minsoo"}],"date":["2018"],"title":["Korean Singing Voice Synthesis System based on an LSTM Recurrent Neural Network"],"container-title":["INTERSPEECH2018. ISCA"],"type":"chapter"},{"citation-number":["20"],"author":[{"family":"Kingma","given":"Diederik P."},{"family":"Ba","given":"Jimmy"}],"date":["2014","2014"],"title":["Adam: A method for stochastic opti- mization"],"note":["arXiv preprint arXiv:1412.6980"],"arxiv":["1412.6980"],"type":null},{"citation-number":["21"],"author":[{"family":"Lee","given":"Juheon"},{"family":"Choi","given":"Hyeong-Seok"},{"family":"Jeon","given":"Chang-Bin"},{"family":"Koo","given":"Junghyun"},{"family":"Lee","given":"Kyogu"}],"date":["2019","2019"],"title":["Adversarially Trained End-to-end Korean Singing Voice Synthesis System"],"note":["arXiv preprint arXiv:1908.01919"],"arxiv":["1908.01919"],"type":null},{"citation-number":["22"],"author":[{"family":"Li","given":"Hao"},{"family":"Kang","given":"Yongguo"},{"family":"Wang","given":"Zhenyu"}],"date":["2018","2018"],"title":["EMPHASIS: An emotional phoneme-based acoustic model for speech synthesis system"],"note":["arXiv preprint arXiv:1806.09276"],"arxiv":["1806.09276"],"type":null},{"citation-number":["23"],"author":[{"family":"Li","given":"Wen"},{"family":"Wang","given":"Limin"},{"family":"Li","given":"Wei"},{"family":"Agustsson","given":"Eirikur"},{"family":"Gool","given":"Luc Van"}],"date":["2017","2017"],"title":["Webvi- sion database: Visual learning and understanding from web data"],"note":["arXiv preprint arXiv:1708.02862"],"arxiv":["1708.02862"],"type":null},{"citation-number":["24"],"author":[{"family":"Lu","given":"Peiling"},{"family":"Wu","given":"Jie"},{"family":"Luan","given":"Jian"},{"family":"Tan","given":"Xu"},{"family":"Zhou","given":"Li"}],"date":["2020","2020"],"title":["XiaoiceSing: A High-Quality and Integrated Singing Voice Synthesis System"],"note":["arXiv preprint arXiv:2006.06261"],"arxiv":["2006.06261"],"type":null},{"citation-number":["25"],"author":[{"family":"McAuliffe","given":"Michael"},{"family":"Socolof","given":"Michaela"},{"family":"Mihuc","given":"Sarah"},{"family":"Wagner","given":"Michael"},{"family":"Sonderegger","given":"Morgan"}],"date":["2017"],"title":["Montreal Forced Aligner: Trainable Text-Speech Alignment Using Kaldi"],"container-title":["Interspeech"],"pages":["498–502"],"type":"chapter"},{"citation-number":["26"],"author":[{"family":"Mesaros","given":"Annamaria"},{"family":"Virtanen","given":"Tuomas"}],"date":["2008"],"title":["Automatic alignment of music audio and lyrics"],"container-title":["Proceedings ofthe 11th Int. Conference on Digital Audio Effects"],"pages":["–08"],"type":"paper-conference"},{"citation-number":["27"],"author":[{"family":"Nakamura","given":"Kazuhiro"},{"family":"Hashimoto","given":"Kei"},{"family":"Oura","given":"Keiichiro"},{"family":"Nankaku","given":"Yoshihiko"},{"family":"Tokuda","given":"Keiichi"}],"date":["2019","2019"],"title":["Singing voice synthesis based on convolutional neural networks"],"note":["arXiv preprint arXiv:1904.06868"],"arxiv":["1904.06868"],"type":null},{"citation-number":["28"],"author":[{"family":"Nguyen","given":"Thi Hao"}],"date":["2018","2018"],"title":["A Study on Correlates ofAcoustic Features to Emotional Singing Voice Synthesis"],"type":null},{"citation-number":["29"],"author":[{"family":"Nishimura","given":"Masanari"},{"family":"Hashimoto","given":"Kei"},{"family":"Oura","given":"Keiichiro"},{"family":"Nankaku","given":"Yoshihiko"},{"family":"Tokuda","given":"Keiichi"}],"date":["2016"],"title":["Singing Voice Synthesis Based on Deep Neural Networks"],"container-title":["Interspeech"],"pages":["2478–2482"],"type":"chapter"},{"citation-number":["30"],"author":[{"family":"Oord","given":"Aaron","particle":"van den"},{"family":"Dieleman","given":"Sander"},{"family":"Zen","given":"Heiga"},{"family":"Simonyan","given":"Karen"},{"family":"Vinyals","given":"Oriol"},{"family":"Graves","given":"Alex"},{"family":"Kalchbrenner","given":"Nal"},{"family":"Senior","given":"Andrew"},{"family":"Kavukcuoglu","given":"Koray"}],"date":["2016","2016"],"title":["Wavenet: A generative model for raw audio"],"note":["arXiv preprint arXiv:1609.03499"],"arxiv":["1609.03499"],"type":null},{"citation-number":["31"],"author":[{"family":"Ping","given":"Wei"},{"family":"Peng","given":"Kainan"},{"family":"Chen","given":"Jitong"}],"date":["2019"],"title":["ClariNet: ParallelWave Generation in End-to-End Text-to-Speech"],"container-title":["ICLR"],"type":"chapter"},{"citation-number":["32"],"author":[{"family":"Qin","given":"Tao"},{"family":"Liu","given":"Tie-Yan"},{"family":"Xu","given":"Jun"},{"family":"Li","given":"Hang"}],"date":["2010","2010"],"title":["LETOR: A benchmark collection for research on learning to rank for information retrieval"],"volume":["13, 4"],"pages":["346–374"],"type":"article-journal","container-title":["Information Retrieval"]},{"citation-number":["33"],"author":[{"family":"Ren","given":"Yi"},{"family":"Hu","given":"Chenxu"},{"family":"Tan","given":"Xu"},{"family":"Qin","given":"Tao"},{"family":"Zhao","given":"Sheng"},{"family":"Zhao","given":"Zhou"},{"family":"Liu","given":"Tie-Yan"}],"date":["2020","2020"],"title":["FastSpeech 2: Fast and High-Quality End-to-End Text-to-Speech"],"note":["arXiv preprint arXiv:2006.04558"],"arxiv":["2006.04558"],"type":null},{"citation-number":["34"],"author":[{"family":"Ren","given":"Yi"},{"family":"Ruan","given":"Yangjun"},{"family":"Tan","given":"Xu"},{"family":"Qin","given":"Tao"},{"family":"Zhao","given":"Sheng"},{"family":"Zhao","given":"Zhou"},{"family":"Liu","given":"Tie-Yan"}],"date":["2019","2019"],"title":["FastSpeech: Fast, Robust and Controllable Text to Speech"],"note":["arXiv preprint arXiv:1905.09263"],"arxiv":["1905.09263"],"type":null},{"citation-number":["35"],"author":[{"family":"Sharma","given":"Bidisha"},{"family":"Gupta","given":"Chitralekha"},{"family":"Li","given":"Haizhou"},{"family":"Wang","given":"Ye"}],"date":["2019"],"title":["Automatic Lyrics-to-audio Alignment on Polyphonic Music Using Singing-adapted Acoustic Models"],"container-title":["ICASSP 2019"],"publisher":["IEEE"],"pages":["396–400"],"type":"chapter"},{"citation-number":["36"],"author":[{"family":"Shen","given":"Jonathan"},{"family":"Pang","given":"Ruoming"},{"family":"Weiss","given":"Ron J."},{"family":"Schuster","given":"Mike"},{"family":"Jaitly","given":"Navdeep"},{"family":"Yang","given":"Zongheng"},{"family":"Chen","given":"Zhifeng"},{"family":"Zhang","given":"Yu"},{"family":"Wang","given":"Yuxuan"},{"family":"Skerrv-Ryan","given":"Rj"},{"others":true}],"date":["2018"],"title":["Natural tts synthesis by conditioning wavenet on mel spectrogram predic- tions"],"container-title":["ICASSP 2018. IEEE"],"pages":["4779–4783"],"type":"chapter"},{"citation-number":["37"],"author":[{"family":"Tachibana","given":"Hideyuki"},{"family":"Uenoyama","given":"Katsuya"},{"family":"Aihara","given":"Shunsuke"}],"date":["2018"],"title":["Efficiently trainable text-to-speech system based on deep convolutional networks with guided attention"],"container-title":["ICASSP 2018. IEEE"],"pages":["4784–4788"],"type":"chapter"},{"citation-number":["38"],"author":[{"family":"Umbert","given":"Marti"},{"family":"Bonada","given":"Jordi"},{"family":"Goto","given":"Masataka"},{"family":"Nakano","given":"Tomoyasu"},{"family":"berg","given":"Johan Sund-"}],"date":["2015","2015"],"title":["Expression control in singing voice synthesis: Features, approaches, evaluation, and challenges"],"volume":["32, 6"],"pages":["55–73"],"type":"article-journal","container-title":["IEEE Signal Processing Magazine"]},{"citation-number":["39"],"author":[{"family":"Vaswani","given":"Ashish"},{"family":"Shazeer","given":"Noam"},{"family":"Parmar","given":"Niki"},{"family":"Uszkoreit","given":"Jakob"},{"family":"Jones","given":"Llion"},{"family":"Gomez","given":"Aidan N."},{"family":"Kaiser","given":"Łukasz"},{"family":"Polosukhin","given":"Illia"}],"date":["2017"],"title":["Attention is all you need"],"container-title":["Advances in Neural Information Processing Systems"],"pages":["5998–6008"],"type":"chapter"},{"citation-number":["40"],"author":[{"family":"Wu","given":"Zhizheng"},{"family":"Watts","given":"Oliver"},{"family":"King","given":"Simon"}],"date":["2016"],"title":["Merlin: An Open Source Neural Network Speech Synthesis System"],"container-title":["SSW"],"pages":["202–207"],"type":"chapter"},{"citation-number":["41"],"author":[{"family":"Yang","given":"Zhilin"},{"family":"Dai","given":"Zihang"},{"family":"Yang","given":"Yiming"},{"family":"Carbonell","given":"Jaime"},{"family":"Salakhutdinov","given":"Russ R."},{"family":"Le","given":"Quoc V."}],"date":["2019"],"title":["Xlnet: Generalized autoregressive pretraining for language understanding"],"container-title":["Advances in neural information processing systems"],"pages":["5754–5764"],"type":"chapter"},{"citation-number":["42"],"author":[{"family":"Yi","given":"Yuan-Hao"},{"family":"Ai","given":"Yang"},{"family":"Ling","given":"Zhen-Hua"},{"family":"Dai","given":"Li-Rong"}],"date":["2019","2019"],"title":["Singing Voice Synthesis Using Deep Autoregressive Neural Networks for Acoustic Modeling"],"type":null},{"citation-number":["43"],"author":[{"family":"Zen","given":"Heiga"},{"family":"Dang","given":"Viet"},{"family":"Clark","given":"Rob"},{"family":"Zhang","given":"Yu"},{"family":"Weiss","given":"Ron J."},{"family":"Jia","given":"Ye"},{"family":"Chen","given":"Zhifeng"},{"family":"Wu","given":"Yonghui"}],"date":["2019","2019"],"title":["LibriTTS: A corpus derived from librispeech for text-to- speech"],"note":["arXiv preprint arXiv:1904.02882"],"arxiv":["1904.02882"],"type":null},{"citation-number":["44"],"author":[{"family":"Zhang","given":"Liqiang"},{"family":"Yu","given":"Chengzhu"},{"family":"Lu","given":"Heng"},{"family":"Weng","given":"Chao"},{"family":"Wu","given":"Yusong"},{"family":"Xie","given":"Xiang"},{"family":"Li","given":"Zijin"},{"family":"Yu","given":"Dong"}],"date":["2019","2019"],"title":["Learning Singing From Speech"],"note":["arXiv preprint arXiv:1912.10128"],"arxiv":["1912.10128"],"type":null}]